showmemutil/__init__.py
showmemutil/showmemutil.py
showmemutil-0.1.1.dist-info/WHEEL
showmemutil-0.1.1.dist-info/METADATA
showmemutil-0.1.1.dist-info/RECORD
